LICENSE
MANIFEST.in
README.md
install_script.py
setup.py
kdAutoTeamviewer/__init__.py
kdAutoTeamviewer/fileutil.py
kdAutoTeamviewer/kdAutoTeamviewer.py
kdAutoTeamviewer/kdAutoTeamviewer.ui
kdAutoTeamviewer.egg-info/PKG-INFO
kdAutoTeamviewer.egg-info/SOURCES.txt
kdAutoTeamviewer.egg-info/dependency_links.txt
kdAutoTeamviewer.egg-info/entry_points.txt
kdAutoTeamviewer.egg-info/not-zip-safe
kdAutoTeamviewer.egg-info/requires.txt
kdAutoTeamviewer.egg-info/top_level.txt