Metadata-Version: 1.2
Name: kdAutoTeamviewer
Version: 1.0.0
Summary: UNKNOWN
Home-page: https://github.com/bkdwei/kdAutoTeamviewer
Author: bkdwei
Author-email: bkdwei@163.com
Maintainer: 韦坤东
Maintainer-email: bkdwei@163.com
License: GPLv3+
Keywords: 远程控制,teamviewer
Platform: any
Classifier: Development Status :: 5 - Production/Stable
Classifier: Environment :: X11 Applications :: Qt
Classifier: Intended Audience :: End Users/Desktop
Classifier: Natural Language :: Chinese (Simplified)
Classifier: Topic :: System :: Filesystems
Classifier: Programming Language :: Python :: 3
Classifier:  License :: OSI Approved :: GNU General Public License v3 or later (GPLv3+)
Classifier: Operating System :: POSIX
Classifier: Operating System :: Microsoft :: Windows
